onvif/__init__.py
onvif/client.py
onvif/operator.py
onvif/cli/__init__.py
onvif/cli/__main__.py
onvif/cli/interactive.py
onvif/cli/main.py
onvif/cli/utils.py
onvif/db/companies.db
onvif/db/products.db
onvif/services/__init__.py
onvif/services/accesscontrol.py
onvif/services/accessrules.py
onvif/services/actionengine.py
onvif/services/analyticsdevice.py
onvif/services/appmgmt.py
onvif/services/authenticationbehavior.py
onvif/services/credential.py
onvif/services/deviceio.py
onvif/services/devicemgmt.py
onvif/services/display.py
onvif/services/doorcontrol.py
onvif/services/imaging.py
onvif/services/media.py
onvif/services/media2.py
onvif/services/provisioning.py
onvif/services/ptz.py
onvif/services/receiver.py
onvif/services/recording.py
onvif/services/replay.py
onvif/services/schedule.py
onvif/services/search.py
onvif/services/thermal.py
onvif/services/uplink.py
onvif/services/analytics/analytics.py
onvif/services/analytics/ruleengine.py
onvif/services/events/events.py
onvif/services/events/notification.py
onvif/services/events/pausable_subscription.py
onvif/services/events/pullpoint.py
onvif/services/events/subscription.py
onvif/services/security/advancedsecurity.py
onvif/services/security/authorizationserver.py
onvif/services/security/dot1x.py
onvif/services/security/jwt.py
onvif/services/security/keystore.py
onvif/services/security/mediasigning.py
onvif/services/security/tlsserver.py
onvif/utils/__init__.py
onvif/utils/discovery.py
onvif/utils/error_handlers.py
onvif/utils/exceptions.py
onvif/utils/parser.py
onvif/utils/service.py
onvif/utils/wsdl.py
onvif/utils/xml_capture.py
onvif/utils/zeep.py
onvif/wsdl/LICENSE.md
onvif/wsdl/schema/common/b-2.xsd
onvif/wsdl/schema/common/bf-2.xsd
onvif/wsdl/schema/common/bw-2.wsdl
onvif/wsdl/schema/common/include
onvif/wsdl/schema/common/mpqf.xsd
onvif/wsdl/schema/common/r-2.xsd
onvif/wsdl/schema/common/rw-2.wsdl
onvif/wsdl/schema/common/soap-envelope
onvif/wsdl/schema/common/t-1.xsd
onvif/wsdl/schema/common/ws-addr.xsd
onvif_python-0.2.9.dist-info/licenses/LICENSE.md
onvif_python-0.2.9.dist-info/METADATA
onvif_python-0.2.9.dist-info/WHEEL
onvif_python-0.2.9.dist-info/entry_points.txt
onvif_python-0.2.9.dist-info/top_level.txt
onvif_python-0.2.9.dist-info/RECORD
