Metadata-Version: 2.4
Name: onvif-python
Version: 0.2.9
Summary: A modern Python library for ONVIF-compliant devices
Author-email: Nirsimetri Technologies® <open@nirsimetri.com>
Maintainer: Kaburagi
License-Expression: MIT
Project-URL: Homepage, https://github.com/nirsimetri/onvif-python
Project-URL: Documentation, https://deepwiki.com/nirsimetri/onvif-python
Project-URL: Changelog, https://github.com/nirsimetri/onvif-python/releases
Keywords: onvif,Camera,onvif-python,ip-camera,cctv,soap,surveillance,cctv cameras,soap-client,onvif-client,onvif-library,onvif-specifications
Classifier: Development Status :: 5 - Production/Stable
Classifier: Environment :: Console
Classifier: Programming Language :: Python :: 3.9
Classifier: Programming Language :: Python :: 3.10
Classifier: Programming Language :: Python :: 3.11
Classifier: Programming Language :: Python :: 3.12
Classifier: Programming Language :: Python :: 3.13
Classifier: Programming Language :: Python :: 3.14
Classifier: Operating System :: OS Independent
Classifier: Intended Audience :: Developers
Classifier: Intended Audience :: Information Technology
Classifier: Intended Audience :: Science/Research
Classifier: Topic :: Software Development :: Libraries
Classifier: Topic :: Software Development :: Libraries :: Python Modules
Classifier: Topic :: Security
Classifier: Topic :: Multimedia :: Video
Classifier: Topic :: Multimedia :: Sound/Audio
Classifier: Topic :: Communications
Classifier: Topic :: Text Processing :: Markup :: XML
Classifier: Natural Language :: English
Classifier: Natural Language :: Indonesian
Requires-Python: >=3.9
License-File: LICENSE.md
Requires-Dist: zeep>=4.3.0
Requires-Dist: requests>=2.32.0
Provides-Extra: dev
Requires-Dist: pytest>=7.0; extra == "dev"
Requires-Dist: black; extra == "dev"
Requires-Dist: flake8; extra == "dev"
Dynamic: license-file
